calc_maker/__init__.py
calc_maker/core.py
calc_maker-0.1.0.dist-info/licenses/LICENSE
calc_maker-0.1.0.dist-info/METADATA
calc_maker-0.1.0.dist-info/WHEEL
calc_maker-0.1.0.dist-info/top_level.txt
calc_maker-0.1.0.dist-info/RECORD
